sqlite_utils_sqlite_lembed/__init__.py
sqlite_utils_sqlite_lembed-0.0.1a8.dist-info/METADATA
sqlite_utils_sqlite_lembed-0.0.1a8.dist-info/WHEEL
sqlite_utils_sqlite_lembed-0.0.1a8.dist-info/entry_points.txt
sqlite_utils_sqlite_lembed-0.0.1a8.dist-info/top_level.txt
sqlite_utils_sqlite_lembed-0.0.1a8.dist-info/RECORD
