Metadata-Version: 2.1
Name: sqlite-utils-sqlite-lembed
Version: 0.0.1a8
Home-page: https://TODO.com
Author: TODO
License: MIT License, Apache License, Version 2.0
Requires-Dist: sqlite-utils
Requires-Dist: sqlite-lembed (==0.0.1-alpha.8)
